README.rst
setup.py
fz/__init__.py
fz.egg-info/PKG-INFO
fz.egg-info/SOURCES.txt
fz.egg-info/dependency_links.txt
fz.egg-info/requires.txt
fz.egg-info/top_level.txt